simpylc/__init__.py
simpylc/__main__.py
simpylc/base.py
simpylc/chart.py
simpylc/coder.py
simpylc/collisions.py
simpylc/engine.py
simpylc/graphics.py
simpylc/gui.py
simpylc/quaternions.py
simpylc/scene.py
simpylc/scene_transformations.jpg
simpylc/simpylc_howto.odt
simpylc/simpylc_howto.pdf
simpylc/simpylcprog.jpg
simpylc/vectors.py
simpylc/accessories/QuartzMS.TTF
simpylc/accessories/freeglut32.vc14.dll
simpylc/accessories/freeglut64.vc14.dll
simpylc/simulations/arduino_led_timer/led_timer.py
simpylc/simulations/arduino_led_timer/native.cpp
simpylc/simulations/arduino_led_timer/timing.py
simpylc/simulations/arduino_led_timer/world.py
simpylc/simulations/arduino_traffic_lights/native.cpp
simpylc/simulations/arduino_traffic_lights/timing.py
simpylc/simulations/arduino_traffic_lights/traffic_lights.py
simpylc/simulations/arduino_traffic_lights/visualisation.py
simpylc/simulations/arduino_traffic_lights/world.py
simpylc/simulations/blinking_light/blinking_light.py
simpylc/simulations/blinking_light/timing.py
simpylc/simulations/blinking_light/world.py
simpylc/simulations/boat/control_server.py
simpylc/simulations/boat/notes.txt
simpylc/simulations/boat/socket_wrapper.py
simpylc/simulations/boat/vessel.py
simpylc/simulations/boat/visualisation.py
simpylc/simulations/boat/world.py
simpylc/simulations/boat/control_client/almanac.py
simpylc/simulations/boat/control_client/captain.py
simpylc/simulations/boat/control_client/constants.py
simpylc/simulations/boat/control_client/crew.py
simpylc/simulations/boat/control_client/current.waypoints
simpylc/simulations/boat/control_client/deckhand.py
simpylc/simulations/boat/control_client/deckhand_twin.py
simpylc/simulations/boat/control_client/helmsman.py
simpylc/simulations/boat/control_client/kml_to_waypoints.py
simpylc/simulations/boat/control_client/kralingse_plas.jpg
simpylc/simulations/boat/control_client/kralingse_plas.kml
simpylc/simulations/car/control_server.py
simpylc/simulations/car/dimensions.py
SimPyLC-3.10.6.dist-info/METADATA
SimPyLC-3.10.6.dist-info/WHEEL
SimPyLC-3.10.6.dist-info/top_level.txt
SimPyLC-3.10.6.dist-info/RECORD
