Metadata-Version: 2.1
Name: SimPyLC
Version: 3.10.6
Summary: SimPyLC PLC simulator, after its C++ big brother that has controlled industrial installations for more than 25 years now. ARDUINO CODE GENERATION ADDED!
Home-page: http://www.qquick.org/educational
Author: Jacques de Hooge
Author-email: jacques.de.hooge@qquick.org
License: qQuickLicence
Keywords: PLC,Arduino,simulator,SimPyLC,emulator,GEATEC
Platform: UNKNOWN
Classifier: Development Status :: 5 - Production/Stable
Classifier: Intended Audience :: Developers
Classifier: Natural Language :: English
Classifier: License :: Other/Proprietary License
Classifier: Topic :: Software Development :: Libraries :: Python Modules
Classifier: Operating System :: Microsoft :: Windows
Classifier: Operating System :: POSIX :: Linux
Classifier: Operating System :: MacOS
Classifier: Programming Language :: Python :: 3.10
Requires-Dist: numpy
Requires-Dist: pyopengl
Requires-Dist: windows-curses ; platform_system == "Windows"
